oncemessage/__init__.py
oncemessage/api.py
oncemessage/db.py
oncemessage/pipeline.py
oncemessage/producer.py
oncemessage-0.0.2.dist-info/METADATA
oncemessage-0.0.2.dist-info/WHEEL
oncemessage-0.0.2.dist-info/top_level.txt
oncemessage-0.0.2.dist-info/RECORD
