Metadata-Version: 2.1
Name: oncemessage
Version: 0.0.2
Summary: A package for faster coding.
Home-page: https://github.com/private_repo/
Author: slipper
Author-email: r2fscg@gmail.com
Classifier: Programming Language :: Python :: 3
Classifier: License :: OSI Approved :: MIT License
Classifier: Operating System :: OS Independent
Requires-Dist: codefast
Requires-Dist: redis
